{"files":{"GitHub Pages.md":{"filePath":"GitHub Pages.md","links":[],"meta":{"page":{"description":"GitHub Pages is an easy way to deploy and host static websites on GitHub."},"slug":"github-pages","tags":[]},"parentNote":"index.md","title":"GitHub Pages","url":"github-pages.html"},"Japanese.md":{"filePath":"Japanese.md","links":[],"meta":null,"parentNote":"index.md","title":"Japanese","url":"Japanese.html"},"Japanese/Grammar.md":{"filePath":"Japanese/Grammar.md","links":[],"meta":null,"parentNote":"Japanese.md","title":"Grammar","url":"Japanese/Grammar.html"},"Japanese/Grammar/grammar.md":{"filePath":"Japanese/Grammar/grammar.md","links":[],"meta":{"page":{"description":"TODO"},"tags":[]},"parentNote":"Japanese/Grammar.md","title":"grammar","url":"Japanese/Grammar/grammar.html"},"Japanese/Milestones.md":{"filePath":"Japanese/Milestones.md","links":[],"meta":null,"parentNote":"Japanese.md","title":"Milestones","url":"Japanese/Milestones.html"},"Japanese/Milestones/jlpt.md":{"filePath":"Japanese/Milestones/jlpt.md","links":[{"resolvedRelTarget":{"contents":"Japanese/Milestones/jlpt.png","tag":"RRTFound"},"unresolvedRelTarget":{"contents":["WikiLinkEmbed","jlpt.png"],"tag":"URTWikiLink"}}],"meta":{"page":{"description":"[[jlpt.png]]"},"tags":[]},"parentNote":"Japanese/Milestones.md","title":"JLPT","url":"Japanese/Milestones/jlpt.html"},"Japanese/Milestones/media.md":{"filePath":"Japanese/Milestones/media.md","links":[{"resolvedRelTarget":{"contents":"Japanese/Milestones/media.png","tag":"RRTFound"},"unresolvedRelTarget":{"contents":["WikiLinkEmbed","media.png"],"tag":"URTWikiLink"}}],"meta":{"page":{"description":"[[media.png]]"},"tags":[]},"parentNote":"Japanese/Milestones.md","title":"Media Coverage % Based on Top K Words Known","url":"Japanese/Milestones/media.html"},"Japanese/Resources.md":{"filePath":"Japanese/Resources.md","links":[],"meta":null,"parentNote":"Japanese.md","title":"Resources","url":"Japanese/Resources.html"},"Japanese/Resources/resources.md":{"filePath":"Japanese/Resources/resources.md","links":[],"meta":{"page":{"description":"Best Resource for memorizing vocab based on interested media"},"tags":[]},"parentNote":"Japanese/Resources.md","title":"Resources","url":"Japanese/Resources/resources.html"},"index.md":{"filePath":"index.md","links":[],"meta":{"page":{"description":"Hi, I’m Hidden."},"tags":[]},"parentNote":null,"title":"Hidden System","url":""}},"version":1}